bamboo_lca/__init__.py
bamboo_lca/background_importer.py
bamboo_lca/datapackage_builder.py
bamboo_lca/foreground_importer.py
bamboo_lca/lca_wrapper.py
bamboo_lca/metadata_manager.py
bamboo_lca/uncertainty_handler.py
bamboo_lca/uncertainty_importer.py
bamboo_lca/utils.py
bamboo_lca-0.1.5.dist-info/licenses/LICENSE
bamboo_lca-0.1.5.dist-info/METADATA
bamboo_lca-0.1.5.dist-info/WHEEL
bamboo_lca-0.1.5.dist-info/top_level.txt
bamboo_lca-0.1.5.dist-info/RECORD
