Metadata-Version: 2.4
Name: bamboo_lca
Version: 0.1.5
Summary: This is a Python package designed to import external input-output databases to brightway, such as EXIOBASE. In addition, it can assist you to model different types of uncertainty analysis or scenario analysis with datapackage matrix data.
Author: Ning An
License-Expression: BSD-3-Clause
Requires-Python: >=3.7
License-File: LICENSE
Requires-Dist: numpy
Requires-Dist: pandas
Requires-Dist: scipy
Requires-Dist: typing
Dynamic: license-file
